autophrasex/__init__.py
autophrasex/autophrase.py
autophrasex/callbacks.py
autophrasex/extractors.py
autophrasex/reader.py
autophrasex/selector.py
autophrasex/tokenizer.py
autophrasex/utils.py
tests/__init__.py
tests/autophrase_test.py
tests/tokenizer_test.py
autophrasex-0.3.1.dist-info/LICENSE
autophrasex-0.3.1.dist-info/METADATA
autophrasex-0.3.1.dist-info/WHEEL
autophrasex-0.3.1.dist-info/top_level.txt
autophrasex-0.3.1.dist-info/RECORD
