Metadata-Version: 2.1
Name: autophrasex
Version: 0.3.1
Summary: Automated Phrase Mining from Massive Text Corpora in Python.
Home-page: https://github.com/luozhouyang/AutoPhraseX
Author: ZhouYang Luo
Author-email: zhouyang.luo@gmail.com
License: Apache Software License
Platform: UNKNOWN
Classifier: Programming Language :: Python :: 3
Classifier: Programming Language :: Python :: 3.5
Classifier: Programming Language :: Python :: 3.6
Classifier: Programming Language :: Python :: 3.7
Classifier: Programming Language :: Python :: 3.8
Classifier: License :: OSI Approved :: Apache Software License
Classifier: Operating System :: OS Independent
Classifier: Topic :: Scientific/Engineering :: Artificial Intelligence
Requires-Dist: jieba
Requires-Dist: naive-stopwords
Requires-Dist: scikit-learn
Requires-Dist: opencc
